LICENSE.txt
README.md
setup.cfg
setup.py
LinkageMechanism/LinkageMechanism.py
LinkageMechanism/__init__.py
LinkageMechanism.egg-info/PKG-INFO
LinkageMechanism.egg-info/SOURCES.txt
LinkageMechanism.egg-info/dependency_links.txt
LinkageMechanism.egg-info/top_level.txt