Metadata-Version: 1.2
Name: LinkageMechanism
Version: 1.0.0
Summary: App para análise de Mecanismos
Home-page: https://https://github.com/Ze-Maria/LinkageMechanism
Author: José Maria Bezerra
Author-email: zemaria@ufpe.br
License: MIT License
Project-URL: Código fonte, https://github.com/Ze-Maria/LinkageMechanism
Project-URL: Download, https://github.com/Ze-Maria/LinkageMechanism/blob/main/LinkageMechanism.py
Keywords: mechanism linkage ufpe
Platform: UNKNOWN
